Metadata-Version: 2.1
Name: giganticode-codeprep
Version: 1.0.0
Summary: A toolkit for pre-processing large source code corpora
Home-page: http://github.com/giganticode/codeprep
Author: Hlib Babii
Author-email: hlibbabii@gmail.com
License: Apache-2.0
Keywords: big large data source code corpus machine learning pre-processing nlp
Platform: UNKNOWN
Classifier: Development Status :: 3 - Alpha
Classifier: Environment :: Console
Classifier: Intended Audience :: Science/Research
Classifier: License :: OSI Approved :: Apache Software License
Classifier: Natural Language :: English
Classifier: Programming Language :: Python :: 3.6
Classifier: Programming Language :: Python :: 3.7
Classifier: Operating System :: POSIX :: Linux
Classifier: Operating System :: MacOS :: MacOS X
Classifier: Operating System :: Microsoft :: Windows
Classifier: Topic :: Software Development :: Pre-processors
Requires-Python: >=3.6
Requires-Dist: appdirs (==1.4.3)
Requires-Dist: dill (==0.3.1.1)
Requires-Dist: docopt (==0.6.2)
Requires-Dist: docopt-subcommands (==3.0.0)
Requires-Dist: jsons (==1.0.0)
Requires-Dist: nltk (==3.4.5)
Requires-Dist: Pygments (==2.5.2)
Requires-Dist: PyYAML (==5.1.2)
Requires-Dist: regex (==2019.11.1)
Requires-Dist: tqdm (==4.39.0)
